ColorString/ColorString.py
ColorString/__init__.py
ColorString-0.0.2.dist-info/LICENSE
ColorString-0.0.2.dist-info/METADATA
ColorString-0.0.2.dist-info/WHEEL
ColorString-0.0.2.dist-info/top_level.txt
ColorString-0.0.2.dist-info/RECORD
